[{"user_id":"kbeunxk73tx1gy","name":"","email":"jrutledge03@berkeley.edu","lti_ids":[],"days":0,"posts":0,"asks":0,"answers":0,"views":0},{"user_id":"kblb1hinkmlvz","name":"","email":"roxannerubin@berkeley.edu","lti_ids":[],"days":0,"posts":0,"asks":0,"answers":0,"views":0},{"user_id":"kblb1iawfdwwj","name":"","email":"cyx2020@berkeley.edu","lti_ids":[],"days":0,"posts":0,"asks":0,"answers":0,"views":0},{"user_id":"kblb1jb0audxc","name":"","email":"ethanlau@berkeley.edu","lti_ids":[],"days":0,"posts":0,"asks":0,"answers":0,"views":0},{"user_id":"kblb1if1sjhwn","name":"Chandra Sen","email":"chandy10@berkeley.edu","lti_ids":[],"days":3,"posts":0,"asks":0,"answers":0,"views":17},{"user_id":"kblb1im0wrywu","name":"Mona Williams","email":"williams.m@berkeley.edu","lti_ids":[],"days":10,"posts":2,"asks":0,"answers":0,"views":51},{"user_id":"kblb1hyr76fw9","name":"Hannah Han","email":"hhan3@berkeley.edu","lti_ids":[],"days":5,"posts":0,"asks":0,"answers":0,"views":27},{"user_id":"kblb1jza6gfy0","name":"yueyang zhang","email":"zyuey@berkeley.edu","lti_ids":[],"days":5,"posts":0,"asks":0,"answers":0,"views":18},{"user_id":"jrba9r11ynt3yq","name":"Joseph Dixon","email":"jdixon@berkeley.edu","lti_ids":["berkeley.edu_000acc84f0c185947403946f09656fee7c0e18f7.ucberkeley.instructure.com_73e62260156bd0e7fd3cd7c79658c04200e9421a"],"days":0,"posts":0,"asks":0,"answers":0,"views":0},{"user_id":"k5olr4ncsr81f4","name":"jiayi nie","email":"natalie98@berkeley.edu","lti_ids":[],"days":0,"posts":0,"asks":0,"answers":0,"views":0},{"user_id":"kbeumzr0xm1sw","name":"Harrison Tighe","email":"harrisont55@berkeley.edu","lti_ids":[],"days":6,"posts":0,"asks":0,"answers":0,"views":20},{"user_id":"kblb1j6hc3nx8","name":"Shaiyaan","email":"sh2018@berkeley.edu","lti_ids":[],"days":5,"posts":0,"asks":0,"answers":0,"views":24},{"user_id":"kblb1iv2ju3x1","name":"Qintong Cai","email":"cqt@berkeley.edu","lti_ids":[],"days":2,"posts":1,"asks":1,"answers":0,"views":1},{"user_id":"kblb1hgdcn5vx","name":"WenXuan Lai","email":"wenxuan_lai@berkeley.edu","lti_ids":[],"days":1,"posts":0,"asks":0,"answers":0,"views":2},{"user_id":"kblb1ihdo8dwp","name":"ayden jun boyko","email":"aydenjunboyko@berkeley.edu","lti_ids":[],"days":16,"posts":0,"asks":0,"answers":0,"views":13},{"user_id":"kblb1hqtbtnw5","name":"Rushil Ray","email":"rray20@berkeley.edu","lti_ids":[],"days":28,"posts":6,"asks":1,"answers":0,"views":140},{"user_id":"kblb1ijpiyzws","name":"Joshua Cooper","email":"joshfcooper@berkeley.edu","lti_ids":[],"days":20,"posts":4,"asks":1,"answers":0,"views":38},{"user_id":"kblb1j8stu5xa","name":"Jared Fang","email":"jfang03@berkeley.edu","lti_ids":[],"days":31,"posts":0,"asks":0,"answers":0,"views":121},{"user_id":"kblb1kpq21myo","name":"Renhai Zhou","email":"rezhou@berkeley.edu","lti_ids":[],"days":7,"posts":3,"asks":1,"answers":0,"views":55},{"user_id":"kblb1kl32u3yh","name":"Colin Galbraith","email":"cgalbraith@berkeley.edu","lti_ids":[],"days":31,"posts":12,"asks":6,"answers":1,"views":103},{"user_id":"kbhd2peb3xn46e","name":"zheng chang","email":"changzheng990222@berkeley.edu","lti_ids":[],"days":30,"posts":2,"asks":2,"answers":0,"views":121},{"user_id":"kbqtz17y4gz3ua","name":"William Win Soe","email":"williamwinsoe78@berkeley.edu","lti_ids":[],"days":29,"posts":3,"asks":1,"answers":0,"views":97},{"user_id":"j031lbaxctg45n","name":"Aaron Baker","email":"aaronbaker@berkeley.edu","lti_ids":[],"days":59,"posts":211,"asks":0,"answers":89,"views":263},{"user_id":"kbrf1m4vh426zw","name":"Yuan Garcia","email":"yuangarcia@berkeley.edu","lti_ids":[],"days":19,"posts":1,"asks":1,"answers":0,"views":39},{"user_id":"kbswibjmultfp","name":"Anthony Ha","email":"ajh21@berkeley.edu","lti_ids":[],"days":24,"posts":0,"asks":0,"answers":0,"views":113},{"user_id":"kblb1i8mqsbwd","name":"Rebecca Elizabeth Tio","email":"rtio@berkeley.edu","lti_ids":[],"days":31,"posts":5,"asks":5,"answers":0,"views":91},{"user_id":"kblb1gwls5wv9","name":"Melisa Dundar","email":"mdundar@berkeley.edu","lti_ids":[],"days":46,"posts":6,"asks":0,"answers":0,"views":162},{"user_id":"kblb1jk1ml4xl","name":"Alexandra Langer","email":"alexandra07@berkeley.edu","lti_ids":[],"days":58,"posts":17,"asks":2,"answers":0,"views":160},{"user_id":"kblb1h7njouvj","name":"Ryan Fouzdar","email":"ryanfouzdar@berkeley.edu","lti_ids":[],"days":57,"posts":0,"asks":0,"answers":0,"views":164},{"user_id":"kblb1iy421ix3","name":"Hailey Hong Yen Thi Tran","email":"hhytt@berkeley.edu","lti_ids":[],"days":36,"posts":3,"asks":0,"answers":0,"views":88},{"user_id":"kblb1hwcwxjw7","name":"Vinaya Parimi","email":"vinaya.parimi@berkeley.edu","lti_ids":[],"days":38,"posts":1,"asks":0,"answers":1,"views":162},{"user_id":"jl41me8wlxu1ev","name":"LizaBanks Campagna","email":"lizabankscampagna@berkeley.edu","lti_ids":[],"days":4,"posts":0,"asks":0,"answers":0,"views":15},{"user_id":"kblb1k6nm9sy5","name":"Simon Martin","email":"simonmartin2025@berkeley.edu","lti_ids":[],"days":17,"posts":2,"asks":1,"answers":0,"views":90},{"user_id":"kblb1j0hsv4x5","name":"Uta Rassow","email":"utra@berkeley.edu","lti_ids":[],"days":60,"posts":41,"asks":5,"answers":3,"views":166},{"user_id":"kbbgnm89z3g3ol","name":"Raphael Mostov","email":"rmostov@berkeley.edu","lti_ids":["piazza.sandbox_000acc84f0c185947403946f09656fee7c0e18f7.ucberkeley.instructure.com_9cc5ed69a395eb1c8fc30dc3b4d005a9d7321219"],"days":0,"posts":0,"asks":0,"answers":0,"views":0},{"user_id":"kblb1key5u2ye","name":"Taimoor Qureshi","email":"thqureshi@berkeley.edu","lti_ids":[],"days":46,"posts":14,"asks":7,"answers":1,"views":126},{"user_id":"kblb1he2t2avq","name":"Daniela Guerra","email":"danielaguerra@berkeley.edu","lti_ids":[],"days":31,"posts":21,"asks":10,"answers":0,"views":169},{"user_id":"k5k3gg0ig9r72f","name":"Sara Tetsu","email":"satetsu@berkeley.edu","lti_ids":[],"days":1,"posts":0,"asks":0,"answers":0,"views":17},{"user_id":"kblb1ks1lavyr","name":"Ryan Ting","email":"ryanting@berkeley.edu","lti_ids":[],"days":29,"posts":3,"asks":3,"answers":0,"views":126},{"user_id":"j3xjumuxue33n","name":"Evan Gong","email":"evangong@berkeley.edu","lti_ids":["berkeley.edu_000acc84f0c185947403946f09656fee7c0e18f7.ucberkeley.instructure.com_d882bc04a8f9d28cb8dba1318edc242df24dfde2"],"days":7,"posts":0,"asks":0,"answers":0,"views":17},{"user_id":"kblb1kndvljyj","name":"Johnson Nguyen","email":"jhnguyen514@berkeley.edu","lti_ids":[],"days":53,"posts":0,"asks":0,"answers":0,"views":70},{"user_id":"k0wppmerdox695","name":"Gracie Chung","email":"graciechung@berkeley.edu","lti_ids":[],"days":54,"posts":11,"asks":7,"answers":0,"views":126},{"user_id":"kblb1jff8h7xh","name":"Ailun Shi","email":"ailunshi@berkeley.edu","lti_ids":[],"days":54,"posts":13,"asks":3,"answers":0,"views":165},{"user_id":"kblb1iq3h5pwx","name":"Nazrin Mammadova","email":"nazrin@berkeley.edu","lti_ids":[],"days":70,"posts":14,"asks":9,"answers":1,"views":140},{"user_id":"k5cx220nkmv6s3","name":"Rasheed Leggett","email":"rasheedml@berkeley.edu","lti_ids":["berkeley.edu_000acc84f0c185947403946f09656fee7c0e18f7.ucberkeley.instructure.com_38f2ceccc427eef9ed3fc002cf5b4d7068268142"],"days":19,"posts":0,"asks":0,"answers":0,"views":29},{"user_id":"k0wpk8aij5s233","name":"Jason Yu","email":"jayu23@berkeley.edu","lti_ids":["berkeley.edu_000acc84f0c185947403946f09656fee7c0e18f7.ucberkeley.instructure.com_e7d8d105529f233b3ed43a2b12d9e319d50e8cd4"],"days":15,"posts":0,"asks":0,"answers":0,"views":20},{"user_id":"kblb1jd76raxe","name":"Junhua Huang","email":"jhhuang@berkeley.edu","lti_ids":[],"days":28,"posts":1,"asks":0,"answers":0,"views":64},{"user_id":"k0cw0wobhov57q","name":"Thi Huynh","email":"khanhhuynh2111@berkeley.edu","lti_ids":[],"days":41,"posts":8,"asks":1,"answers":0,"views":147},{"user_id":"kblb1jhp1nlxj","name":"Heather Yuan","email":"heather.yuan@berkeley.edu","lti_ids":[],"days":53,"posts":12,"asks":3,"answers":2,"views":152},{"user_id":"k5lrqq8b2ln4b1","name":"Alejandro Guerrero","email":"a.guerrero03@berkeley.edu","lti_ids":["berkeley.edu_000acc84f0c185947403946f09656fee7c0e18f7.ucberkeley.instructure.com_0671a1d0b62d7ed41484518c9f8ea92b3cbee360"],"days":36,"posts":8,"asks":1,"answers":0,"views":112},{"user_id":"jyt7k4voru935z","name":"Ailin Chen","email":"achen87@berkeley.edu","lti_ids":["berkeley.edu_000acc84f0c185947403946f09656fee7c0e18f7.ucberkeley.instructure.com_7fa15616b0f8d50f66c5f8ba2b78b831586eec93"],"days":104,"posts":31,"asks":9,"answers":0,"views":156},{"user_id":"k0wpkofgtgm2ny","name":"Yiheng Li","email":"annayihengli@berkeley.edu","lti_ids":["piazza.sandbox_000acc84f0c185947403946f09656fee7c0e18f7.ucberkeley.instructure.com_e864dbf83c7ceb5354fa905188d4bb7d63b2e5ca","berkeley.edu_000acc84f0c185947403946f09656fee7c0e18f7.ucberkeley.instructure.com_e864dbf83c7ceb5354fa905188d4bb7d63b2e5ca"],"days":102,"posts":0,"asks":0,"answers":0,"views":34},{"user_id":"kblb1jme332xn","name":"Fanyi Lyu","email":"percy_2020@berkeley.edu","lti_ids":[],"days":68,"posts":9,"asks":5,"answers":0,"views":167},{"user_id":"j3nrzzr4lhm4w2","name":"Chris Tam","email":"christam@berkeley.edu","lti_ids":["berkeley.edu_000acc84f0c185947403946f09656fee7c0e18f7.ucberkeley.instructure.com_726db21a844b8c5b105ef81660b6f86ffc9e92fc"],"days":45,"posts":0,"asks":0,"answers":0,"views":49},{"user_id":"jleqebbde8sx","name":"QiWen Li","email":"li.qw@berkeley.edu","lti_ids":["berkeley.edu_000acc84f0c185947403946f09656fee7c0e18f7.ucberkeley.instructure.com_d944ad721077cc42b74dcb99e4e724da92b5dc14"],"days":111,"posts":10,"asks":6,"answers":0,"views":166},{"user_id":"k0wpm2fkze04df","name":"Leon Chen","email":"leonyiliangchen@berkeley.edu","lti_ids":[],"days":58,"posts":9,"asks":3,"answers":0,"views":109},{"user_id":"jzdh11m86md2la","name":"Maxine Sy Chu","email":"maxinesc@berkeley.edu","lti_ids":["berkeley.edu_000acc84f0c185947403946f09656fee7c0e18f7.ucberkeley.instructure.com_89ffc61b4995d758aa9d55617bdd62037154d79c"],"days":75,"posts":1,"asks":1,"answers":0,"views":63},{"user_id":"kblb1ku9b3yyu","name":"Sofia","email":"sofia.amaro@berkeley.edu","lti_ids":["berkeley.edu_000acc84f0c185947403946f09656fee7c0e18f7.ucberkeley.instructure.com_661a5bf28244313a88506077075a28297016fb65"],"days":63,"posts":20,"asks":10,"answers":1,"views":116},{"user_id":"k04kizdgtbq70s","name":"Eden Chun","email":"ekchun@berkeley.edu","lti_ids":["berkeley.edu_000acc84f0c185947403946f09656fee7c0e18f7.ucberkeley.instructure.com_aeb463133e672a76c135cfd7bd038a54e6ba3a6f"],"days":83,"posts":29,"asks":6,"answers":2,"views":134},{"user_id":"jzerqnqp64t2vy","name":"Nicole Yacoub","email":"yacoubnicole@berkeley.edu","lti_ids":["piazza.sandbox_000acc84f0c185947403946f09656fee7c0e18f7.ucberkeley.instructure.com_7d26296876b777f4d15b570cd2d258a40eac8515"],"days":0,"posts":0,"asks":0,"answers":0,"views":0},{"user_id":"jjvubklz4545fr","name":"Samhita Sen","email":"samhitasen@berkeley.edu","lti_ids":[],"days":74,"posts":51,"asks":0,"answers":24,"views":213},{"user_id":"j6okkwf2yo5","name":"Andrew Burke","email":"aburke225@berkeley.edu","lti_ids":["berkeley.edu_000acc84f0c185947403946f09656fee7c0e18f7.ucberkeley.instructure.com_7ef247b644a9080cc30f953453f01e3a02797422"],"days":52,"posts":4,"asks":0,"answers":2,"views":104},{"user_id":"kblb1jut602xv","name":"Sana Khan","email":"sanakhan@berkeley.edu","lti_ids":[],"days":61,"posts":2,"asks":2,"answers":0,"views":117},{"user_id":"jzw7tcr8v4vng","name":"Kayla Zhu","email":"kaylaz98@berkeley.edu","lti_ids":["berkeley.edu_000acc84f0c185947403946f09656fee7c0e18f7.ucberkeley.instructure.com_c7a35d16a2c5f109208c549a5eb0847f4a9533cb"],"days":112,"posts":14,"asks":3,"answers":0,"views":163},{"user_id":"kblb1gyv36evb","name":"Jeffrey Huang","email":"jeff0827@berkeley.edu","lti_ids":[],"days":80,"posts":13,"asks":6,"answers":0,"views":168},{"user_id":"k5k3g0ae7yt6qv","name":"Grace Lu","email":"gracelu@berkeley.edu","lti_ids":[],"days":70,"posts":29,"asks":14,"answers":1,"views":87},{"user_id":"kblb1jx3watxy","name":"Jordan Schwartz","email":"jordanschwartz@berkeley.edu","lti_ids":[],"days":111,"posts":16,"asks":3,"answers":1,"views":161},{"user_id":"jqwt5a9oe7s5cq","name":"Jonathan Estrada","email":"_jonathan@berkeley.edu","lti_ids":[],"days":54,"posts":1,"asks":1,"answers":0,"views":115},{"user_id":"k7vbekvb74o4qy","name":"Blayden Lee","email":"blayden@berkeley.edu","lti_ids":[],"days":86,"posts":8,"asks":5,"answers":0,"views":158},{"user_id":"jm70vln09i52ak","name":"Brian Blair","email":"ninthcat@berkeley.edu","lti_ids":[],"days":95,"posts":0,"asks":0,"answers":0,"views":5},{"user_id":"kb9t9rkwze74zp","name":"Paul","email":"fentresspaul@berkeley.edu","lti_ids":[],"days":84,"posts":25,"asks":14,"answers":0,"views":70},{"user_id":"k5cx23ma223752","name":"Zia Bajwa","email":"ziabajwa@berkeley.edu","lti_ids":["berkeley.edu_000acc84f0c185947403946f09656fee7c0e18f7.ucberkeley.instructure.com_bc36d6f933165b04a82fd69bbaef596292fd73a7"],"days":48,"posts":0,"asks":0,"answers":0,"views":2},{"user_id":"k5cx1zd765g6p7","name":"Beata Gold","email":"btgold@berkeley.edu","lti_ids":[],"days":32,"posts":0,"asks":0,"answers":0,"views":6},{"user_id":"kblb1h2xk9pve","name":"Narmin","email":"narmin@berkeley.edu","lti_ids":[],"days":68,"posts":32,"asks":13,"answers":0,"views":62},{"user_id":"jzw8ee70de122h","name":"Christopher Jin","email":"chris.jin@berkeley.edu","lti_ids":[],"days":86,"posts":0,"asks":0,"answers":0,"views":66},{"user_id":"kblb1ha054xvm","name":"Irene Yang","email":"ireneyang@berkeley.edu","lti_ids":[],"days":110,"posts":27,"asks":6,"answers":1,"views":168},{"user_id":"kbrh0j3dbxh61y","name":"Kyaw Swar Ye Myint","email":"kyawswaryemyint@berkeley.edu","lti_ids":["berkeley.edu_000acc84f0c185947403946f09656fee7c0e18f7.ucberkeley.instructure.com_5743beab12e4e5ecefef0db1a16cec4a1e10596e"],"days":108,"posts":40,"asks":7,"answers":3,"views":162},{"user_id":"jkx7gfvsykk4g1","name":"Sarita Maharajh","email":"smaharajh@berkeley.edu","lti_ids":["berkeley.edu_000acc84f0c185947403946f09656fee7c0e18f7.ucberkeley.instructure.com_62aba02b6ea0f3fb8ea66c2f742926a4c83977f4"],"days":71,"posts":2,"asks":1,"answers":0,"views":164},{"user_id":"jlmyog9hjzndi","name":"Anjali Bhat","email":"anjalicbhat@berkeley.edu","lti_ids":["berkeley.edu_000acc84f0c185947403946f09656fee7c0e18f7.ucberkeley.instructure.com_803537564d29576990b21387ca92d7136e805830"],"days":81,"posts":1,"asks":1,"answers":0,"views":111},{"user_id":"j6sjhnh48b17ny","name":"Daisy Knobloch","email":"daisyknobloch@berkeley.edu","lti_ids":["berkeley.edu_000acc84f0c185947403946f09656fee7c0e18f7.ucberkeley.instructure.com_99661cc8ef693e92669c8452b669128ab2583954"],"days":98,"posts":0,"asks":0,"answers":0,"views":13},{"user_id":"jl74v40qcf54fh","name":"Yolanda Shen","email":"yashen@berkeley.edu","lti_ids":["berkeley.edu_000acc84f0c185947403946f09656fee7c0e18f7.ucberkeley.instructure.com_7bfa677a0ff81da4df2ca56b8ce19529e776c2d6"],"days":119,"posts":137,"asks":0,"answers":52,"views":267},{"user_id":"j6lrx2aetb3al","name":"Kellyann Ye","email":"kellyann_ye@berkeley.edu","lti_ids":[],"days":99,"posts":12,"asks":0,"answers":2,"views":49},{"user_id":"jzvg9cdrocf149","name":"Vaibhav Mohata","email":"vaibhav.mohata@berkeley.edu","lti_ids":[],"days":0,"posts":0,"asks":0,"answers":0,"views":0},{"user_id":"jnezdcjrXSAY","name":"Deleree Schornack","email":"delereeschornack@berkeley.edu","lti_ids":["berkeley.edu_000acc84f0c185947403946f09656fee7c0e18f7.ucberkeley.instructure.com_8f55e06263a7aef8eb4905b390ef319ad9e44ca1"],"days":108,"posts":2,"asks":0,"answers":0,"views":109},{"user_id":"k5k3g57si3i6uy","name":"Suraj Rajan","email":"suraj.m.rajan@berkeley.edu","lti_ids":[],"days":55,"posts":0,"asks":0,"answers":0,"views":17},{"user_id":"jzerq9q1pys2io","name":"Natasha Raut","email":"natasharaut@berkeley.edu","lti_ids":[],"days":0,"posts":0,"asks":0,"answers":0,"views":0},{"user_id":"jzvg97s4lfcym","name":"Benjamin Michael Pierias","email":"bpierias@berkeley.edu","lti_ids":[],"days":52,"posts":0,"asks":0,"answers":0,"views":1},{"user_id":"jzw93ye0t5q4fs","name":"Yishu Chao","email":"ychao_814@berkeley.edu","lti_ids":["extension.berkeley.edu_000acc84f0c185947403946f09656fee7c0e18f7.ucberkeley.instructure.com_2da77d83837c9fec77da94bf72364c5b492cdf27"],"days":120,"posts":14,"asks":0,"answers":4,"views":90},{"user_id":"k5cx24dp35p75g","name":"Jonathan","email":"jonathansli@berkeley.edu","lti_ids":["berkeley.edu_000acc84f0c185947403946f09656fee7c0e18f7.ucberkeley.instructure.com_4cbe25825daeccd3f56b8bdf22c0c05215f015c9"],"days":0,"posts":0,"asks":0,"answers":0,"views":0},{"user_id":"kblb1gryzs5v2","name":"Mika Burgess","email":"mikanoelle@berkeley.edu","lti_ids":[],"days":34,"posts":0,"asks":0,"answers":0,"views":35},{"user_id":"j6lrx76auoq3dk","name":"Murtaza Ali","email":"murtaza5152.ali@gmail.com","lti_ids":[],"days":97,"posts":11,"asks":0,"answers":3,"views":94},{"user_id":"kaiuz89rkz6op","name":"Weiwei Wu","email":"weiwei.wu@berkeley.edu","lti_ids":["berkeley.edu_000acc84f0c185947403946f09656fee7c0e18f7.ucberkeley.instructure.com_eb4e2b33089f9d7020e9a2843a708462dbdebe74"],"days":109,"posts":9,"asks":7,"answers":0,"views":83},{"user_id":"jzlnq6smu8j2zr","name":"Sarah Varghese","email":"svsarah01@berkeley.edu","lti_ids":[],"days":49,"posts":0,"asks":0,"answers":0,"views":18},{"user_id":"k2mecny94t964j","name":"Miranda Aochi","email":"maochi@berkeley.edu","lti_ids":[],"days":86,"posts":0,"asks":0,"answers":0,"views":122},{"user_id":"j6lrwxyz73s37g","name":"Lam Pham","email":"lampham468@berkeley.edu","lti_ids":["berkeley.edu_000acc84f0c185947403946f09656fee7c0e18f7.ucberkeley.instructure.com_a43e19ee4d3a629f272bb37597a64c5c751ca36c"],"days":101,"posts":14,"asks":0,"answers":13,"views":71},{"user_id":"jktvhtxbw3n6fa","name":"Jerry Xu","email":"jerryxu@berkeley.edu","lti_ids":["berkeley.edu_000acc84f0c185947403946f09656fee7c0e18f7.ucberkeley.instructure.com_d52fd19805cf59a7966e6a8579ce37e8a2bca2ba"],"days":0,"posts":0,"asks":0,"answers":0,"views":0},{"user_id":"jcdzxitmzf9130","name":"Danielle Swords","email":"daniswords@berkeley.edu","lti_ids":[],"days":113,"posts":10,"asks":0,"answers":4,"views":241},{"user_id":"ixvdi0ss3on510","name":"Maxson Yang","email":"maxsonyang@berkeley.edu","lti_ids":["berkeley.edu_000acc84f0c185947403946f09656fee7c0e18f7.ucberkeley.instructure.com_03f7c4ba7ae54571e50864e30df6ec0cc0c1aa4c"],"days":58,"posts":84,"asks":0,"answers":39,"views":136}]